panos_upgrade_assurance/__init__.py
panos_upgrade_assurance/check_firewall.py
panos_upgrade_assurance/exceptions.py
panos_upgrade_assurance/firewall_proxy.py
panos_upgrade_assurance/snapshot_compare.py
panos_upgrade_assurance/utils.py
panos_upgrade_assurance-2.0.1.dist-info/LICENSE
panos_upgrade_assurance-2.0.1.dist-info/METADATA
panos_upgrade_assurance-2.0.1.dist-info/WHEEL
panos_upgrade_assurance-2.0.1.dist-info/RECORD
