Metadata-Version: 2.1
Name: panos-upgrade-assurance
Version: 2.0.1
Summary: 
Author: Palo Alto Networks
Requires-Python: >=3.8
Classifier: License :: OSI Approved :: MIT License
Classifier: Operating System :: OS Independent
Classifier: Programming Language :: Python :: 3
Classifier: Programming Language :: Python :: 3.8
Classifier: Programming Language :: Python :: 3.9
Classifier: Programming Language :: Python :: 3.10
Classifier: Programming Language :: Python :: 3.11
Classifier: Programming Language :: Python :: 3.12
Classifier: Programming Language :: Python :: 3.13
Requires-Dist: packaging (>=22.0)
Requires-Dist: pan-os-python (>=1.8,<2.0)
Requires-Dist: pyopenssl (>=23.2,<24.0)
Requires-Dist: typing-extensions (>=4.13.2,<5.0) ; python_version < "3.10"
Requires-Dist: xmltodict (>=0.12.0,<0.15.0)
